ttml_to_json/__init__.py
ttml_to_json/__main__.py
ttml_to_json/cli.py
ttml_to_json-0.2.dist-info/LICENSE
ttml_to_json-0.2.dist-info/METADATA
ttml_to_json-0.2.dist-info/WHEEL
ttml_to_json-0.2.dist-info/entry_points.txt
ttml_to_json-0.2.dist-info/top_level.txt
ttml_to_json-0.2.dist-info/RECORD
