Metadata-Version: 2.1
Name: ttml-to-json
Version: 0.2
Summary: Convert TTML to JSON
Home-page: https://github.com/simonw/ttml-to-json
Author: Simon Willison
License: Apache License, Version 2.0
Project-URL: Issues, https://github.com/simonw/ttml-to-json/issues
Project-URL: CI, https://github.com/simonw/ttml-to-json/actions
Project-URL: Changelog, https://github.com/simonw/ttml-to-json/releases
Requires-Python: >=3.7
License-File: LICENSE
Requires-Dist: click
Provides-Extra: test
Requires-Dist: pytest ; extra == 'test'
